version4plos.py
version4plos-1.0.1.dist-info/DESCRIPTION.rst
version4plos-1.0.1.dist-info/METADATA
version4plos-1.0.1.dist-info/RECORD
version4plos-1.0.1.dist-info/WHEEL
version4plos-1.0.1.dist-info/entry_points.txt
version4plos-1.0.1.dist-info/metadata.json
version4plos-1.0.1.dist-info/top_level.txt
