Metadata-Version: 2.0
Name: version4plos
Version: 1.0.1
Summary: Console app and Python API for automated tracking of PLOS LaTeX template versions
Home-page: https://github.com/petarmaric/version4plos
Author: Petar Maric
Author-email: petarmaric@uns.ac.rs
License: BSD
Platform: UNKNOWN
Classifier: Development Status :: 5 - Production/Stable
Classifier: Environment :: Console
Classifier: Intended Audience :: Developers
Classifier: Intended Audience :: Science/Research
Classifier: License :: OSI Approved :: BSD License
Classifier: Operating System :: OS Independent
Classifier: Programming Language :: Python :: 2.7
Classifier: Topic :: Scientific/Engineering
Classifier: Topic :: Text Processing :: Markup :: LaTeX
Classifier: Topic :: Utilities
Provides-Extra: dev
Requires-Dist: lxml (~=4.4)
Requires-Dist: requests (~=2.22)
Provides-Extra: dev
Requires-Dist: pylint (~=1.9); extra == 'dev'
